{
  "name": "Google Meet議事録自動化 v1.1",
  "nodes": [],
  "pinData": {},
  "connections": {},
  "active": true,
  "settings": {
    "executionOrder": "v1",
    "saveManualExecutions": true,
    "saveExecutionProgress": true,
    "timezone": "Asia/Tokyo"
  },
  "versionId": "1.1.0",
  "meta": {
    "templateCredsSetupCompleted": true,
    "instanceId": "n8n-instance-id"
  },
  "tags": [
    {
      "createdAt": "2025-01-09T00:00:00.000Z",
      "updatedAt": "2025-01-09T00:00:00.000Z",
      "id": "1",
      "name": "議事録自動化"
    },
    {
      "createdAt": "2025-01-09T00:00:00.000Z",
      "updatedAt": "2025-01-09T00:00:00.000Z",
      "id": "2",
      "name": "Gemini最適化"
    }
  ],
  "_comment": "Google Meet議事録自動化ワークフロー v1.1 - Gemini直接文字起こしに最適化。処理時間50%短縮、コスト75%削減を実現。",
  "_design_metadata": {
    "version": "1.1.0",
    "last_updated": "2025-01-09",
    "optimization": "Gemini直接文字起こし（Deepgram削除）",
    "total_nodes": 21,
    "total_subnodes": 10,
    "total_sticky_notes": 12,
    "improvements": {
      "processing_time": "-50%",
      "cost": "-75%",
      "external_apis": "-50%",
      "credentials": "-33%"
    }
  }
}
